{
  "1": {
    "rf__max_depth": 3,
    "rf__min_samples_leaf": 2,
    "rf__min_samples_split": 7,
    "rf__n_estimators": 5,
    "select__k": 4
  },
  "2": {
    "rf__max_depth": 2,
    "rf__min_samples_leaf": 5,
    "rf__min_samples_split": 3,
    "rf__n_estimators": 3,
    "select__k": 4
  },
  "3": {
    "rf__max_depth": 2,
    "rf__min_samples_leaf": 3,
    "rf__min_samples_split": 10,
    "rf__n_estimators": 2,
    "select__k": 8
  },
  "4": {
    "rf__max_depth": 3,
    "rf__min_samples_leaf": 5,
    "rf__min_samples_split": 10,
    "rf__n_estimators": 5,
    "select__k": 3
  },
  "5": {
    "rf__max_depth": 3,
    "rf__min_samples_leaf": 5,
    "rf__min_samples_split": 3,
    "rf__n_estimators": 3,
    "select__k": 7
  },
  "6": {
    "rf__max_depth": 2,
    "rf__min_samples_leaf": 5,
    "rf__min_samples_split": 2,
    "rf__n_estimators": 5,
    "select__k": 3
  },
  "7": {
    "rf__max_depth": 3,
    "rf__min_samples_leaf": 4,
    "rf__min_samples_split": 2,
    "rf__n_estimators": 3,
    "select__k": 4
  },
  "8": {
    "rf__max_depth": 3,
    "rf__min_samples_leaf": 5,
    "rf__min_samples_split": 6,
    "rf__n_estimators": 5,
    "select__k": 5
  },
  "9": {
    "rf__max_depth": 2,
    "rf__min_samples_leaf": 4,
    "rf__min_samples_split": 10,
    "rf__n_estimators": 5,
    "select__k": 5
  },
  "10": {
    "rf__max_depth": 2,
    "rf__min_samples_leaf": 5,
    "rf__min_samples_split": 3,
    "rf__n_estimators": 3,
    "select__k": 4
  }
}